py_rete/__init__.py
py_rete/alpha.py
py_rete/beta.py
py_rete/bind_node.py
py_rete/common.py
py_rete/filter_node.py
py_rete/join_node.py
py_rete/ncc_node.py
py_rete/negative_node.py
py_rete/network.py
py_rete/pnode.py
py_rete/utils.py
py_rete-0.0.6.dist-info/LICENSE
py_rete-0.0.6.dist-info/METADATA
py_rete-0.0.6.dist-info/WHEEL
py_rete-0.0.6.dist-info/pbr.json
py_rete-0.0.6.dist-info/top_level.txt
py_rete-0.0.6.dist-info/RECORD
