Metadata-Version: 2.1
Name: py-rete
Version: 0.0.6
Summary: A basic Python implementation of the RETE algorithm.
Home-page: https://pypi.python.org/pypi/py_rete/
Author: Christopher J. MacLellan
Author-email: maclellan.christopher@gmail.com
License: MIT
Project-URL: Source Code, https://github.com/cmaclell/naive-rete
Platform: UNKNOWN
Classifier: Development Status :: 4 - Beta
Classifier: Intended Audience :: Science/Research
Classifier: Topic :: Scientific/Engineering :: Artificial Intelligence
Classifier: License :: OSI Approved :: MIT License
Classifier: Programming Language :: Python
Classifier: Programming Language :: Python :: 3
Classifier: Programming Language :: Python :: 3.7
Classifier: Programming Language :: Python :: Implementation :: PyPy
